design.sv
// Code your design here
`timescale 1ns / 1ps
module FULL_ADDER(
 input In_0,
 input In_1,
 input Cin,
 output Sout,
 output Cout
 );
wire t1,t2,t3;
xor(Sout,In_0,In_1,Cin);
and(t1,In_0,In_1);
and(t2,In_1,Cin);
and(t3,Cin,In_0);
or(Cout,t1,t2,t3);
endmodule

testbench.sv
// Code your testbench here
// or browse Examples
// Code your testbench here
// or browse Examples
`timescale 1ns / 1ps
module FULL_ADDER_TF;
// Inputs
reg In_0;
reg In_1;
reg Cin;
// Outputs
wire Sout;
wire Cout;
// Instantiate the Unit Under Test (UUT)
FULL_ADDER uut (
.In_0(In_0),
.In_1(In_1),
.Cin(Cin),
.Sout(Sout), 
  .Cout(Cout)
);
initial begin
// Initialize Inputs
In_0 = 0;
In_1 = 0;
Cin = 0;
// Wait 100 ns for global reset to finish
#100;
// Add stimulus here
In_0 = 0;
In_1 = 0;
Cin = 1;
// Wait 100 ns for global reset to finish
#100;
In_0 = 0;
In_1 = 1;
Cin = 0;
// Wait 100 ns for global reset to finish
#100;
In_0 = 0;
In_1 = 1;
Cin = 1;
// Wait 100 ns for global reset to finish
#100;
In_0 = 1;
In_1 = 0;
Cin = 0;
// Wait 100 ns for global reset to finish
#100;
In_0 = 1;
In_1 = 0;
Cin = 1;
// Wait 100 ns for global reset to finish
#100;
In_0 = 1;
In_1 = 1;
Cin = 0;
// Wait 100 ns for global reset to finish
#100;
In_0 = 1;
In_1 = 1;
Cin = 1;
// Wait 100 ns for global reset to finish
#100;
end
  initial 
    begin 
      $dumpfile("half_gate.vcd");
      $dumpvars;
                end
endmodule

half_gate.vcd
$date
	Mon Oct 26 14:48:34 2020
$end
$version
	QuestaSim Version 2020.1_1
$end
$timescale
	1ps
$end

$scope module FULL_ADDER_TF $end
$var reg 1 ! In_0 $end
$var reg 1 " In_1 $end
$var reg 1 # Cin $end
$var wire 1 $ Sout $end
$var wire 1 % Cout $end

$scope module uut $end
$var wire 1 & In_0 $end
$var wire 1 ' In_1 $end
$var wire 1 ( Cin $end
$var wire 1 $ Sout $end
$var wire 1 % Cout $end
$var wire 1 ) t1 $end
$var wire 1 * t2 $end
$var wire 1 + t3 $end
$upscope $end
$upscope $end

$scope begin std $end
$upscope $end
$enddefinitions $end
#0
$dumpvars
0!
0"
0#
0$
0%
0)
0*
0+
0(
0'
0&
$end
#100000
1#
1(
1$
#200000
1"
0#
1'
0(
#300000
1#
1(
1*
0$
1%
#400000
1!
0"
0#
1&
0'
0(
0*
1$
0%
#500000
1#
1(
1+
0$
1%
#600000
1"
0#
1'
0(
0+
1)
#700000
1#
1(
1+
1*
1$
